seven_circumstances/__init__.py
seven_circumstances-0.0.2.dist-info/LICENSE
seven_circumstances-0.0.2.dist-info/METADATA
seven_circumstances-0.0.2.dist-info/WHEEL
seven_circumstances-0.0.2.dist-info/top_level.txt
seven_circumstances-0.0.2.dist-info/RECORD
