Metadata-Version: 2.1
Name: seven-circumstances
Version: 0.0.2
Summary: 'Seven circumstances' are the foundation of 'inquisitive semantics'.
Author-email: Alexander Fedotov <alex.fedotov@aol.com>
Project-URL: Homepage, https://github.com/seven-circumstances/seven-circumstances
Project-URL: Bug Tracker, https://github.com/seven-circumstances/seven-circumstances/issues
Classifier: Programming Language :: Python :: 3
Classifier: License :: OSI Approved :: MIT License
Classifier: Operating System :: OS Independent
Requires-Python: >=3.10
License-File: LICENSE
